<?xml version="1.0" encoding="UTF-8"?>
<!DOCTYPE generatorConfiguration PUBLIC "-//mybatis.org//DTD MyBatis Generator Configuration 1.0//EN" "http://mybatis.org/dtd/mybatis-generator-config_1_0.dtd">
<generatorConfiguration>
  <context id="context1">
    <jdbcConnection connectionURL="jdbc:mysql://localhost:3306/oil" driverClass="com.mysql.jdbc.Driver" password="root" userId="root" />
    <javaModelGenerator targetPackage="com.crx.pojo" targetProject="ooo/src/main/java" />
    <sqlMapGenerator targetPackage="com.crx.mapper" targetProject="ooo/src/main/java" />
    <javaClientGenerator targetPackage="com.crx.mapper" targetProject="ooo/src/main/java" type="XMLMAPPER" />
    <table tableName="user"></table>
  </context>
</generatorConfiguration>